omniquestor/Omniquestor.py
omniquestor/__init__.py
Omniquestor-0.0.3.dist-info/LICENSE
Omniquestor-0.0.3.dist-info/METADATA
Omniquestor-0.0.3.dist-info/WHEEL
Omniquestor-0.0.3.dist-info/top_level.txt
Omniquestor-0.0.3.dist-info/RECORD
