Metadata-Version: 2.1
Name: Omniquestor
Version: 0.0.3
Summary: A simple utility for handling auth header python requests.
Author-email: Jason Cain <jason@caincraft.com>
License: Copyright (c) 2018 The Python Packaging Authority        
Project-URL: Homepage, https://github.com/caincraft/omniquestor
Project-URL: Bug Tracker, https://github.com/caincraft/omniquestor/issues
Classifier: Programming Language :: Python :: 3
Classifier: License :: OSI Approved :: MIT License
Classifier: Operating System :: OS Independent
Requires-Python: >=3.8
License-File: LICENSE
